{"group": "男甲","littlegroup": "A","name":"化学"}
{"group": "男甲","littlegroup": "A","name":"生科"}
{"group": "男甲","littlegroup": "A","name":"信科"}
{"group": "男甲","littlegroup": "A","name":"城环"}
{"group": "男甲","littlegroup": "A","name":"地空"}
{"group": "男甲","littlegroup": "A","name":"法学"}
{"group": "男甲","littlegroup": "B","name":"医学"}
{"group": "男甲","littlegroup": "B","name":"数学"}
{"group": "男甲","littlegroup": "B","name":"环科"}
{"group": "男甲","littlegroup": "B","name":"经济"}
{"group": "男甲","littlegroup": "B","name":"软微"}
{"group": "男甲","littlegroup": "B","name":"外院"}
{"group": "男乙","littlegroup": "A","name":"电子"}
{"group": "男乙","littlegroup": "A","name":"社会"}
{"group": "男乙","littlegroup": "A","name":"教历"}
{"group": "男乙","littlegroup": "A","name":"中文"}
{"group": "男乙","littlegroup": "B","name":"叉院"}
{"group": "男乙","littlegroup": "B","name":"国关"}
{"group": "男乙","littlegroup": "B","name":"光华"}
{"group": "男乙","littlegroup": "B","name":"马院"}
{"group": "男乙","littlegroup": "C","name":"物理"}
{"group": "男乙","littlegroup": "C","name":"材料"}
{"group": "男乙","littlegroup": "C","name":"信管"}
{"group": "男乙","littlegroup": "C","name":"计算机"}
{"group": "男乙","littlegroup": "D","name":"工学"}
{"group": "男乙","littlegroup": "D","name":"新传"}
{"group": "男乙","littlegroup": "D","name":"未农"}
{"group": "男乙","littlegroup": "D","name":"元培"}
{"group": "男乙","littlegroup": "E","name":"集电"}
{"group": "男乙","littlegroup": "E","name":"智能"}
{"group": "男乙","littlegroup": "E","name":"国体"}
{"group": "男乙","littlegroup": "E","name":"政管"}
{"group": "男乙","littlegroup": "F","name":"心理"}
{"group": "男乙","littlegroup": "F","name":"哲学"}
{"group": "男乙","littlegroup": "F","name":"燕京"}
{"group": "男乙","littlegroup": "F","name":"艺术"}
{"group": "女甲","littlegroup": "A","name":"外院"}
{"group": "女甲","littlegroup": "A","name":"法学"}
{"group": "女甲","littlegroup": "A","name":"元培"}
{"group": "女甲","littlegroup": "A","name":"马院"}
{"group": "女甲","littlegroup": "A","name":"医学"}
{"group": "女甲","littlegroup": "A","name":"化学"}
{"group": "女甲","littlegroup": "A","name":"信科"}
{"group": "女甲","littlegroup": "A","name":"新传"}
{"group": "女乙","littlegroup": "A","name":"物理"}
{"group": "女乙","littlegroup": "A","name":"光经"}
{"group": "女乙","littlegroup": "A","name":"燕京"}
{"group": "女乙","littlegroup": "A","name":"信管"}
{"group": "女乙","littlegroup": "A","name":"中文"}
{"group": "女乙","littlegroup": "B","name":"城环"}
{"group": "女乙","littlegroup": "B","name":"心理"}
{"group": "女乙","littlegroup": "B","name":"教哲"}
{"group": "女乙","littlegroup": "B","name":"社会"}
{"group": "女乙","littlegroup": "C","name":"数学"}
{"group": "女乙","littlegroup": "C","name":"生历"}
{"group": "女乙","littlegroup": "C","name":"国关"}
{"group": "女乙","littlegroup": "C","name":"政管"}